{
  "series": "manufacturing-engineering",
  "title": "Manufacturing Engineering",
  "version": 1,
  "totalParts": 12,
  "security": {
    "method": "xor-b64",
    "salt": "mfg-eng-2026"
  },
  "questions": [
    {
      "id": "me-q001",
      "part": 1,
      "difficulty": "beginner",
      "type": "mcq",
      "question": "Which manufacturing process removes material to create the final shape?",
      "options": [
        "Casting (pouring molten material into a mold)",
        "Machining (cutting, drilling, milling)",
        "Forging (shaping with compressive force)",
        "Additive manufacturing (3D printing)"
      ],
      "explanation": "Machining is subtractive manufacturing: material is removed by cutting tools. Includes: turning (lathe), milling, drilling, grinding. Produces high precision but generates waste (chips).",
      "articleSlug": "manufacturing-engineering-processes",
      "tags": [
        "machining",
        "subtractive"
      ],
      "answer": "XA=="
    },
    {
      "id": "me-q002",
      "part": 2,
      "difficulty": "intermediate",
      "type": "true-false",
      "question": "Injection molding is economical for producing 10 custom parts.",
      "explanation": "Injection molding has high tooling costs ($10K-$500K for molds) but very low per-part cost at volume. Economical at 1000+ parts. For 10 parts: use CNC machining, 3D printing, or vacuum casting.",
      "articleSlug": "manufacturing-engineering-injection-molding",
      "tags": [
        "injection molding",
        "economics"
      ],
      "answer": "CwcLXgA="
    },
    {
      "id": "me-q003",
      "part": 3,
      "difficulty": "intermediate",
      "type": "fill-blank",
      "question": "In CNC machining, the programmed path that the cutting tool follows is called the ___.",
      "acceptAlso": [
        "tool path",
        "G-code path",
        "cutting path"
      ],
      "explanation": "The toolpath is generated from CAD geometry by CAM software. It defines every movement of the cutting tool: approach, cutting passes, retract. Expressed in G-code (G0: rapid, G1: linear cut, G2/G3: arcs).",
      "articleSlug": "manufacturing-engineering-cnc",
      "tags": [
        "CNC",
        "toolpath",
        "G-code"
      ],
      "answer": "TxIIQgkeBllaEg=="
    },
    {
      "id": "me-q004",
      "part": 4,
      "difficulty": "advanced",
      "type": "scenario",
      "question": "You need to manufacture 50,000 aluminum smartphone cases per month. Which process gives the best quality-cost-speed combination?",
      "scenario": {
        "context": "Dimensions: 150×75×8mm, ±0.05mm tolerance, mirror finish required.",
        "constraints": [
          "50,000/month volume",
          "6061-T6 aluminum",
          "Fine surface finish (Ra < 0.4μm)",
          "Complex internal features (antenna lines, button holes)"
        ]
      },
      "options": [
        "CNC machining from billet — highest precision but slow and expensive at volume",
        "Die casting + CNC finish machining — fast casting for shape + precision machining for critical features",
        "Extrusion + stamping — cheapest but can't achieve required tolerances",
        "3D printing (DMLS) — flexible but far too slow for 50K/month"
      ],
      "explanation": "Apple's approach: die-cast near-net-shape (fast, cheap at volume), then CNC machine critical surfaces and features (precision where needed). Combines die casting speed with CNC accuracy. Neither alone is optimal at this volume+precision.",
      "articleSlug": "manufacturing-engineering-high-volume",
      "tags": [
        "die casting",
        "CNC",
        "volume production"
      ],
      "answer": "XA=="
    },
    {
      "id": "me-q005",
      "part": 5,
      "difficulty": "advanced",
      "type": "matching",
      "question": "Match each manufacturing process to its ideal application:",
      "pairs": {
        "left": [
          "Forging",
          "Sheet metal stamping",
          "Investment casting",
          "FDM 3D printing"
        ],
        "right": [
          "High-strength structural parts (crankshafts, connecting rods)",
          "High-volume thin parts (car body panels, brackets)",
          "Complex geometries in metal (turbine blades, jewelry)",
          "Prototyping and low-volume custom parts"
        ]
      },
      "explanation": "Forging: grain flow alignment → strongest parts. Stamping: fastest for thin sheet parts (1000s/hour). Investment casting: nearly any geometry possible (lost-wax process). FDM: no tooling cost, design freedom.",
      "articleSlug": "manufacturing-engineering-process-selection",
      "tags": [
        "process selection",
        "manufacturing"
      ],
      "answer": "NlZLHElcSx5v"
    },
    {
      "id": "me-q006",
      "part": 6,
      "difficulty": "advanced",
      "type": "calculation",
      "question": "A CNC milling operation uses: spindle speed 8000 RPM, 4-flute end mill, feed per tooth 0.1mm. What's the feed rate (mm/min)?",
      "formula": "Feed rate = Spindle_speed × Teeth × Feed_per_tooth",
      "unit": "mm/min",
      "tolerance": 0,
      "explanation": "Feed rate = 8000 RPM × 4 flutes × 0.1 mm/tooth = 3200 mm/min. This determines how fast the tool traverses. Too fast: tool breakage, poor finish. Too slow: rubbing, heat buildup, poor productivity.",
      "articleSlug": "manufacturing-engineering-cutting-parameters",
      "tags": [
        "feed rate",
        "CNC",
        "cutting"
      ],
      "answer": "XlRXHQ=="
    }
  ]
}