{
  "series": "cmsis",
  "title": "CMSIS",
  "version": 1,
  "totalParts": 20,
  "security": {
    "method": "xor-b64",
    "salt": "cmsis-fw-2026"
  },
  "questions": [
    {
      "id": "cm-q001",
      "part": 1,
      "difficulty": "beginner",
      "type": "mcq",
      "question": "What does CMSIS stand for?",
      "options": [
        "Common Microcontroller Software Interface Standard",
        "Cortex Microcontroller Software Interface Standard",
        "Chip Manufacturing Software Integration System",
        "Controller Memory System Interface Specification"
      ],
      "explanation": "CMSIS (Cortex Microcontroller Software Interface Standard) is an ARM standard providing a hardware abstraction layer for Cortex-M processors. It standardizes access to core peripherals (NVIC, SysTick, MPU) across vendors.",
      "articleSlug": "cmsis-introduction",
      "tags": [
        "CMSIS",
        "ARM",
        "fundamentals"
      ],
      "answer": "Ug=="
    },
    {
      "id": "cm-q002",
      "part": 2,
      "difficulty": "intermediate",
      "type": "true-false",
      "question": "CMSIS-Core provides direct register access to vendor-specific peripherals (UART, SPI, ADC).",
      "explanation": "CMSIS-Core only covers ARM-designed core peripherals: NVIC (interrupts), SysTick (timer), SCB (system control), MPU (memory protection). Vendor peripherals require vendor-specific HAL/drivers or CMSIS-Driver standard.",
      "articleSlug": "cmsis-core",
      "tags": [
        "CMSIS-Core",
        "peripherals"
      ],
      "answer": "BQwfGhY="
    },
    {
      "id": "cm-q003",
      "part": 3,
      "difficulty": "intermediate",
      "type": "fill-blank",
      "question": "In CMSIS, the function to set an interrupt priority is NVIC_Set___().",
      "acceptAlso": [
        "priority",
        "NVIC_SetPriority"
      ],
      "explanation": "NVIC_SetPriority(IRQn, priority) sets the priority of an interrupt. Lower numbers = higher priority. NVIC_EnableIRQ(), NVIC_DisableIRQ(), and NVIC_SetPriority() are the three most-used CMSIS NVIC functions.",
      "articleSlug": "cmsis-nvic",
      "tags": [
        "NVIC",
        "interrupts",
        "priority"
      ],
      "answer": "QT0BABxfDwNUEA=="
    },
    {
      "id": "cm-q004",
      "part": 4,
      "difficulty": "advanced",
      "type": "code-output",
      "question": "What does this CMSIS code do?",
      "code": "SCB->AIRCR = (0x5FA << SCB_AIRCR_VECTKEY_Pos) |\n             (5 << SCB_AIRCR_PRIGROUP_Pos);",
      "acceptAlso": [
        "configures priority grouping",
        "sets PRIGROUP to 5",
        "sets priority group"
      ],
      "explanation": "Writing to AIRCR requires the key 0x5FA in VECTKEY. PRIGROUP=5 means: of the 8 priority bits, 2 are preemption priority (4 levels) and 6 are sub-priority. This controls nested interrupt behavior.",
      "articleSlug": "cmsis-priority-grouping",
      "tags": [
        "AIRCR",
        "priority grouping"
      ],
      "answer": "QR4WHQANDxlZV0JAQxMZUxkBRAkFREZJElERAgYZGkMBV1ldEAcWS19TCxpZFVddQFVXWxMZGgYdAUZBDVBZRkVDHgYLXl0UHkJAWUZPSk8="
    },
    {
      "id": "cm-q005",
      "part": 5,
      "difficulty": "advanced",
      "type": "matching",
      "question": "Match each CMSIS component to its purpose:",
      "pairs": {
        "left": [
          "CMSIS-Core",
          "CMSIS-DSP",
          "CMSIS-RTOS2",
          "CMSIS-NN"
        ],
        "right": [
          "Standardized access to Cortex-M core registers and NVIC",
          "Optimized signal processing library (FFT, filters, matrix ops)",
          "Generic RTOS API (portable across FreeRTOS, RTX, Zephyr)",
          "Neural network inference on microcontrollers"
        ]
      },
      "explanation": "CMSIS is a family of standards: Core (hardware abstraction), DSP (math library), RTOS2 (OS abstraction), NN (ML inference), Driver (peripheral API), Pack (software distribution).",
      "articleSlug": "cmsis-ecosystem",
      "tags": [
        "CMSIS components",
        "ecosystem"
      ],
      "answer": "OF1fWF8fSkRw"
    },
    {
      "id": "cm-q006",
      "part": 6,
      "difficulty": "advanced",
      "type": "debug",
      "question": "Interrupt-driven UART receive stops working after priority configuration change. Find the bug:",
      "code": "// Before (working):\nNVIC_SetPriority(USART2_IRQn, 5);\nNVIC_EnableIRQ(USART2_IRQn);\n\n// After (broken):\nNVIC_SetPriority(SysTick_IRQn, 4);\nNVIC_SetPriority(USART2_IRQn, 5);\nHAL_NVIC_SetPriorityGrouping(NVIC_PRIORITYGROUP_0);\nNVIC_EnableIRQ(USART2_IRQn);",
      "options": [
        "PRIORITYGROUP_0 means ALL 8 bits are sub-priority, 0 bits preemption — UART can't preempt anything",
        "SysTick at priority 4 is now higher than UART at 5, blocking UART",
        "Must call NVIC_SetPriority AFTER SetPriorityGrouping",
        "HAL function mixed with CMSIS functions causes conflict"
      ],
      "explanation": "PRIORITYGROUP_0 gives 0 preemption bits and all sub-priority bits. With no preemption levels, NO interrupt can preempt another — all have effective preemption priority 0. If any higher-priority ISR is running, UART ISR waits indefinitely.",
      "articleSlug": "cmsis-interrupt-priority",
      "tags": [
        "priority grouping",
        "NVIC",
        "debugging"
      ],
      "answer": "Uw=="
    }
  ]
}